kugelaudio/__init__.py
kugelaudio/client.py
kugelaudio/exceptions.py
kugelaudio/models.py
kugelaudio/py.typed
kugelaudio/streaming.py
kugelaudio/livekit/__init__.py
kugelaudio/livekit/_plugin.py
kugelaudio/livekit/models.py
kugelaudio/livekit/tts.py
kugelaudio-0.2.1.dist-info/METADATA
kugelaudio-0.2.1.dist-info/WHEEL
kugelaudio-0.2.1.dist-info/licenses/LICENSE
kugelaudio-0.2.1.dist-info/RECORD
