Metadata-Version: 2.4
Name: kugelaudio
Version: 0.2.1
Summary: Official Python SDK for KugelAudio TTS API
Project-URL: Homepage, https://kugelaudio.com
Project-URL: Documentation, https://docs.kugelaudio.com
Project-URL: Repository, https://github.com/kugelaudio/kugelaudio-python
Author-email: KugelAudio <support@kugelaudio.com>
License: MIT
License-File: LICENSE
Keywords: audio,streaming,text-to-speech,tts,websocket
Classifier: Development Status :: 4 - Beta
Classifier: Intended Audience :: Developers
Classifier: License :: OSI Approved :: MIT License
Classifier: Programming Language :: Python :: 3
Classifier: Programming Language :: Python :: 3.9
Classifier: Programming Language :: Python :: 3.10
Classifier: Programming Language :: Python :: 3.11
Classifier: Programming Language :: Python :: 3.12
Classifier: Programming Language :: Python :: 3.13
Classifier: Topic :: Multimedia :: Sound/Audio :: Speech
Requires-Python: >=3.9
Requires-Dist: httpx>=0.24.0
Requires-Dist: pydantic>=2.0.0
Requires-Dist: websockets>=11.0
Provides-Extra: dev
Requires-Dist: pytest-asyncio>=0.21.0; extra == 'dev'
Requires-Dist: pytest>=7.0.0; extra == 'dev'
Provides-Extra: livekit
Requires-Dist: aiohttp>=3.8.0; extra == 'livekit'
Requires-Dist: livekit-agents>=1.0.0; extra == 'livekit'
